rename_musicfiles/__init__.py
rename_musicfiles/rename_musicfiles.py
rename_musicfiles-0.1.5.dist-info/entry_points.txt
rename_musicfiles-0.1.5.dist-info/LICENSE
rename_musicfiles-0.1.5.dist-info/WHEEL
rename_musicfiles-0.1.5.dist-info/METADATA
rename_musicfiles-0.1.5.dist-info/RECORD
