Metadata-Version: 2.1
Name: rename_musicfiles
Version: 0.1.5
Summary: A very simple script that renames audio files based on their tags to a hardcoded pattern
Home-page: https://github.com/The-Judge/rename_musicfiles
License: UNKNOWN
Author: Marc Richter
Author-email: mail@marc-richter.info
Classifier: License :: OSI Approved :: MIT License
Classifier: Environment :: Console
Classifier: Programming Language :: Python
Classifier: Topic :: Multimedia :: Sound/Audio
Requires-Dist: phrydy >=2.0.0
